streamlit_image_zoom_with_caption/__init__.py
streamlit_image_zoom_with_caption-0.0.5.dist-info/LICENSE
streamlit_image_zoom_with_caption-0.0.5.dist-info/METADATA
streamlit_image_zoom_with_caption-0.0.5.dist-info/WHEEL
streamlit_image_zoom_with_caption-0.0.5.dist-info/top_level.txt
streamlit_image_zoom_with_caption-0.0.5.dist-info/RECORD
